MANIFEST.in
README.html
README.rst
pyproject.toml
setup.py
antenna_optimizer/Version.py
antenna_optimizer/__init__.py
antenna_optimizer/antenna_model.py
antenna_optimizer/coaxmodel.py
antenna_optimizer/folded.py
antenna_optimizer/folded_3ele.py
antenna_optimizer/folded_bc.py
antenna_optimizer/folded_bigrefl.py
antenna_optimizer/hb9cv.py
antenna_optimizer/hf_folded.py
antenna_optimizer/hf_fuchs.py
antenna_optimizer/hf_inverted_v.py
antenna_optimizer/logper.py
antenna_optimizer/multi_dipole.py
antenna_optimizer/statstool.py
antenna_optimizer/tl.py
antenna_optimizer/transmission.py
antenna_optimizer.egg-info/PKG-INFO
antenna_optimizer.egg-info/SOURCES.txt
antenna_optimizer.egg-info/dependency_links.txt
antenna_optimizer.egg-info/entry_points.txt
antenna_optimizer.egg-info/requires.txt
antenna_optimizer.egg-info/top_level.txt