Metadata-Version: 2.1
Name: antenna-optimizer
Version: 0.3
Summary: Optimize antennas using NEC and a genetic algorithm
Home-page: https://github.com/schlatterbeck/antenna-optimizer
Author: Ralf Schlatterbeck
Author-email: Ralf Schlatterbeck <rsc@runtux.com>
License: BSD License
Project-URL: Homepage, https://github.com/schlatterbeck/antenna-optimizer
Project-URL: Bug Tracker, https://github.com/schlatterbeck/antenna-optimizer/issues
Platform: Any
Classifier: Development Status :: 5 - Production/Stable
Classifier: License :: OSI Approved :: BSD License
Classifier: Operating System :: OS Independent
Classifier: Programming Language :: Python
Classifier: Intended Audience :: Developers
Classifier: Intended Audience :: Science/Research
Classifier: Programming Language :: Python :: 2
Classifier: Programming Language :: Python :: 2.7
Classifier: Programming Language :: Python :: 3
Classifier: Programming Language :: Python :: 3.5
Classifier: Programming Language :: Python :: 3.6
Classifier: Programming Language :: Python :: 3.7
Classifier: Programming Language :: Python :: 3.8
Classifier: Programming Language :: Python :: 3.9
Classifier: Programming Language :: Python :: 3.10
Classifier: Programming Language :: Python :: 3.11
Requires-Python: >=3.7
